tm.py
TournamentMaster-3.1.0.dist-info/DESCRIPTION.rst
TournamentMaster-3.1.0.dist-info/METADATA
TournamentMaster-3.1.0.dist-info/RECORD
TournamentMaster-3.1.0.dist-info/WHEEL
TournamentMaster-3.1.0.dist-info/entry_points.txt
TournamentMaster-3.1.0.dist-info/metadata.json
TournamentMaster-3.1.0.dist-info/top_level.txt
