Metadata-Version: 2.0
Name: TournamentMaster
Version: 3.1.0
Summary: CLI for running tournaments between chess engines
Home-page: https://github.com/Khold6458/TournamentMaster
Author: Simon Chen
Author-email: khold6458@gmail.com
License: GPLv3
Keywords: chess engine tournament
Platform: UNKNOWN
Classifier: Development Status :: 3 - Alpha
Classifier: License :: OSI Approved :: GNU General Public License v3 (GPLv3)
Classifier: Topic :: Games/Entertainment :: Board Games
Classifier: Programming Language :: Python :: 3
Classifier: Programming Language :: Python :: 3.3
Classifier: Programming Language :: Python :: 3.4
Classifier: Programming Language :: Python :: 3.5
Classifier: Programming Language :: Python :: 3.6
Requires-Dist: click
Requires-Dist: python-chess
